hep_viz/__init__.py
hep_viz/cli.py
hep_viz/data_processor.py
hep_viz/server.py
hep_viz/templates/graph_index.html
hep_viz/templates/index.html
hep_viz-0.1.5.dist-info/licenses/LICENSE
tests/conftest.py
tests/test_data_processor.py
tests/test_fastjet_integration.py
tests/test_server.py
hep_viz-0.1.5.dist-info/METADATA
hep_viz-0.1.5.dist-info/WHEEL
hep_viz-0.1.5.dist-info/entry_points.txt
hep_viz-0.1.5.dist-info/top_level.txt
hep_viz-0.1.5.dist-info/RECORD
