Metadata-Version: 2.4
Name: hep-viz
Version: 0.1.5
Summary: A local visualizer for HEP data
Author-email: Finnbar Wilson <finnbareason@gmail.com>
License: MIT License
Classifier: Programming Language :: Python :: 3
Classifier: License :: OSI Approved :: MIT License
Classifier: Operating System :: OS Independent
Requires-Python: >=3.8
License-File: LICENSE
Requires-Dist: typer
Requires-Dist: fastapi
Requires-Dist: uvicorn
Requires-Dist: pandas
Requires-Dist: numpy
Requires-Dist: pyarrow
Requires-Dist: datasets
Requires-Dist: fastjet
Dynamic: license-file
